jaggr/__init__.py
jaggr/aggregator.py
jaggr-0.0.1.dist-info/LICENSE
jaggr-0.0.1.dist-info/METADATA
jaggr-0.0.1.dist-info/WHEEL
jaggr-0.0.1.dist-info/top_level.txt
jaggr-0.0.1.dist-info/RECORD
